sopel_trakt/__init__.py
sopel_trakt-0.2.1.dist-info/COPYING
sopel_trakt-0.2.1.dist-info/METADATA
sopel_trakt-0.2.1.dist-info/WHEEL
sopel_trakt-0.2.1.dist-info/entry_points.txt
sopel_trakt-0.2.1.dist-info/top_level.txt
sopel_trakt-0.2.1.dist-info/RECORD
