Metadata-Version: 2.1
Name: sopel-trakt
Version: 0.2.1
Summary: A Sopel plugin to fetch users' recent Trakt plays
Author-email: Shane Donohoe <shane@donohoe.cc>
Maintainer-email: dgw <dgw@technobabbl.es>
License: EFL-2.0
Project-URL: Homepage, https://github.com/dgw/sopel-trakt
Project-URL: Bug Tracker, https://github.com/dgw/sopel-trakt/issues
Keywords: sopel,plugin,bot,irc
Platform: Linux x86, x86-64
Classifier: Intended Audience :: Developers
Classifier: Intended Audience :: System Administrators
Classifier: License :: Eiffel Forum License (EFL)
Classifier: License :: OSI Approved :: Eiffel Forum License
Classifier: Topic :: Communications :: Chat :: Internet Relay Chat
Requires-Python: <4,>=3.8
License-File: COPYING
Requires-Dist: sopel >=7.1
Requires-Dist: requests
